moogpy/__init__.py
moogpy/atmos.py
moogpy/atomic.py
moogpy/synthesis.py
moogpy/utils.py
moogpy-1.0.2.dist-info/LICENSE
moogpy-1.0.2.dist-info/METADATA
moogpy-1.0.2.dist-info/WHEEL
moogpy-1.0.2.dist-info/top_level.txt
moogpy-1.0.2.dist-info/RECORD
